[
  {
    "date": "5 January 2026",
    "title": "The Air Navigation (Restriction of Flying) (Prescott, Merseyside) (Emergency) Regulations 2025",
    "link": "http://www.legislation.gov.uk/id/uksi/2025/1374",
    "summary": "No explanatory summary available.",
    "country": "United Kingdom"
  },
  {
    "date": "5 January 2026",
    "title": "The Air Navigation (Restriction of Flying) (Mountain Ash) (Emergency) Regulations 2025",
    "link": "http://www.legislation.gov.uk/id/uksi/2025/1373",
    "summary": "No explanatory summary available.",
    "country": "United Kingdom"
  },
  {
    "date": "5 January 2026",
    "title": "The Air Navigation (Restriction of Flying) (Helicopter Flight) Regulations 2025",
    "link": "http://www.legislation.gov.uk/id/uksi/2025/1364",
    "summary": "No explanatory summary available.",
    "country": "United Kingdom"
  },
  {
    "date": "2 January 2026",
    "title": "The Helios Renewable Energy Project Order 2025",
    "link": "http://www.legislation.gov.uk/id/uksi/2025/1372",
    "summary": "No explanatory summary available.",
    "country": "United Kingdom"
  }
]